{
  "signal_idx": 23,
  "signal_length": 49906,
  "ground_truth_symbols": [
    "4",
    "3",
    "*",
    "7",
    "5",
    "A",
    "6",
    "A",
    "4"
  ],
  "timestamp": "2025-12-16T22:26:40.990038",
  "success": true,
  "stft_params": {
    "window_length": 256,
    "overlap": 128,
    "frame_step": 128
  },
  "freq_clustering": {
    "n_clusters": 3,
    "cluster_centers": [
      1033.59375,
      1076.66015625,
      1507.32421875
    ]
  },
  "changepoints_summary": [
    {
      "cluster_id": 0,
      "selected_freq": 947.4609375,
      "n_changepoints": 8,
      "changepoints": [
        11392,
        11648,
        15872,
        16384,
        17024,
        18304,
        29696,
        30208
      ]
    },
    {
      "cluster_id": 3,
      "selected_freq": 861.328125,
      "n_changepoints": 2,
      "changepoints": [
        19584,
        22656
      ]
    },
    {
      "cluster_id": 4,
      "selected_freq": 1378.125,
      "n_changepoints": 3,
      "changepoints": [
        25984,
        28800,
        29056
      ]
    }
  ],
  "period_analysis": {
    "n_original_periods": 12,
    "n_filtered_periods": 12,
    "n_removed_outliers": 0,
    "statistics": {
      "q25": 0.023219954648526078,
      "q75": 0.1306122448979592,
      "iqr": 0.10739229024943311,
      "lower_bound": -0.1378684807256236
    }
  },
  "matches": [
    {
      "match_index": 0,
      "assigned_symbol": "4",
      "verified_symbol": "0",
      "primary_low_freq": 947.4609375,
      "primary_high_freq": 1378.125,
      "period_start": 0.5282539682539683,
      "period_end": 0.7198185941043084,
      "period_duration": 0.19156462585034015,
      "symbol_match": false
    },
    {
      "match_index": 1,
      "assigned_symbol": "3",
      "verified_symbol": "0",
      "primary_low_freq": 947.4609375,
      "primary_high_freq": 1378.125,
      "period_start": 0.7198185941043084,
      "period_end": 0.7430385487528345,
      "period_duration": 0.023219954648526078,
      "symbol_match": false
    },
    {
      "match_index": 2,
      "assigned_symbol": "*",
      "verified_symbol": "0",
      "primary_low_freq": 947.4609375,
      "primary_high_freq": 1378.125,
      "period_start": 0.7430385487528345,
      "period_end": 0.7720634920634921,
      "period_duration": 0.029024943310657598,
      "symbol_match": false
    },
    {
      "match_index": 3,
      "assigned_symbol": "7",
      "verified_symbol": "0",
      "primary_low_freq": 947.4609375,
      "primary_high_freq": 1378.125,
      "period_start": 0.7720634920634921,
      "period_end": 0.8301133786848073,
      "period_duration": 0.058049886621315196,
      "symbol_match": false
    },
    {
      "match_index": 4,
      "assigned_symbol": "5",
      "verified_symbol": "8",
      "primary_low_freq": 861.328125,
      "primary_high_freq": 1378.125,
      "period_start": 0.8301133786848073,
      "period_end": 0.8881632653061224,
      "period_duration": 0.058049886621315196,
      "symbol_match": false
    },
    {
      "match_index": 5,
      "assigned_symbol": "A",
      "verified_symbol": "8",
      "primary_low_freq": 861.328125,
      "primary_high_freq": 1378.125,
      "period_start": 0.8881632653061224,
      "period_end": 1.0274829931972789,
      "period_duration": 0.13931972789115646,
      "symbol_match": false
    },
    {
      "match_index": 6,
      "assigned_symbol": "6",
      "verified_symbol": "8",
      "primary_low_freq": 861.328125,
      "primary_high_freq": 1378.125,
      "period_start": 1.0274829931972789,
      "period_end": 1.1784126984126984,
      "period_duration": 0.1509297052154195,
      "symbol_match": false
    },
    {
      "match_index": 7,
      "assigned_symbol": "A",
      "verified_symbol": "0",
      "primary_low_freq": 947.4609375,
      "primary_high_freq": 1378.125,
      "period_start": 1.1784126984126984,
      "period_end": 1.3061224489795917,
      "period_duration": 0.12770975056689343,
      "symbol_match": false
    },
    {
      "match_index": 8,
      "assigned_symbol": "4",
      "verified_symbol": "0",
      "primary_low_freq": 947.4609375,
      "primary_high_freq": 1378.125,
      "period_start": 1.3177324263038548,
      "period_end": 1.3467573696145125,
      "period_duration": 0.029024943310657598,
      "symbol_match": false
    }
  ]
}